theory_snake/__init__.py
theory_snake/chord_utils.py
theory_snake/consts.py
theory_snake/note_utils.py
theory_snake/scale_builder.py
theory_snake/guitar_utils/__init__.py
theory_snake/guitar_utils/fretboard_builder.py
theory_snake/guitar_utils/guitar_chord_utils.py
theory_snake/guitar_utils/string_builder.py
theory_snake/guitar_utils/tuning_utils.py
theory_snake/models/chord_model.py
theory_snake-0.3.0.dist-info/METADATA
theory_snake-0.3.0.dist-info/WHEEL
theory_snake-0.3.0.dist-info/RECORD
