Metadata-Version: 2.4
Name: theory_snake
Version: 0.3.0
Summary: A simple Python library for generating music chords and scales.
Author-email: Omkar Pradhan <omkarelectric892@gmail.com>
Classifier: License :: OSI Approved :: MIT License
Classifier: Operating System :: OS Independent
Classifier: Programming Language :: Python :: 3
Classifier: Topic :: Multimedia :: Sound/Audio :: Analysis
Requires-Python: >=3.8
